{
  "size": 0,
  "query": {
    "dis_max": {
      "queries": [{
        "bool": {
          "should": [{
            "nested": {
              "query": {
                "match": {
                  "dimension_filter_nested.name": {
                    "query": "Meine produktkategorie wellendurchmesser"
                  }
                }
              },
              "path": "dimension_filter_nested"
            }
          }]
        }
      }]
    }
  },
  "aggregations": {
    "dimension_name--category-meine-produktkategorie-system-metric-language-de": {
      "filter": {
        "bool": {
          "must": [{
            "terms": {
              "taxonomy.raw": ["/Meine produktkategorie"],
              "boost": 1.0
            }
          }]
        }
      },
      "aggregations": {
        "dimension_name": {
          "nested": {
            "path": "dimension_filter_nested"
          },
          "aggregations": {
            "dimension_name": {
              "terms": {
                "field": "dimension_filter_nested.name.raw",
                "size": 10
              }
            }
          }
        }
      }
    }
  }
}
